{"288493503":"No Good to Visit","288493514":"Super Good","288493527":"Not Visited","288579468":"No Good to Visit","288579474":"Pending","289414428":"Pending","289414430":"Visited","289414435":"No Good to Visit","289457564":"Visited","289486712":"No Good to Visit","289486714":"No Good to Visit","289495631":"No Good to Visit","289495648":"No Good to Visit","289495653":"Visited","289511306":"Not Visited","289526802":"No Good to Visit","289575748":"Visited","289581176":"No Good to Visit","289581197":"Visited","289581458":"Pending","289581467":"Pending","289581472":"Not Visited","289637466":"Visited","289637471":"No Good to Visit","289637473":"Visited","289637475":"Visited","289724937":"Not Visited","289724943":"No Good to Visit","289725428":"Visited","289871824":"No Good to Visit","289896961":"No Good to Visit","289963737":"No Good to Visit","289977240":"Not Visited","289977270":"Super Good","289983933":"Visited","290003753":"Super Good","290009082":"Super Good","290014350":"Super Good","290014354":"No Good to Visit","290014356":"No Good to Visit","290024096":"Super Good","290024873":"No Good to Visit","290024874":"Pending","290027879":"Visited","290029829":"Pending","290030765":"No Good to Visit","290030771":"Pending","290030775":"Visited","290034777":"Visited"}